{"TopTags":[{"Rank":1,"Tag":"\u00E7erkezk\u00F6y","Tweets":34},{"Rank":2,"Tag":"kar\u015F\u0131yaka","Tweets":17},{"Rank":3,"Tag":"\uC9C0\uAD6C\uC5D0\uC11C\uB144\uC9C0\uC131\uC544_\uD658\uC601\uD574","Tweets":16},{"Rank":4,"Tag":"bornova","Tweets":15},{"Rank":5,"Tag":"\u4E16\u754C\u676F","Tweets":14},{"Rank":6,"Tag":"ImACeleb","Tweets":11},{"Rank":7,"Tag":"kapakl\u0131","Tweets":9},{"Rank":8,"Tag":"alsancak","Tweets":7},{"Rank":9,"Tag":"cigli","Tweets":7},{"Rank":10,"Tag":"\u00FCcretlishow","Tweets":7}]}